keypad/__init__.py
keypad/keypad.py
keypad/py.typed
keypad_io-0.1.0.dist-info/LICENSE
keypad_io-0.1.0.dist-info/METADATA
keypad_io-0.1.0.dist-info/WHEEL
keypad_io-0.1.0.dist-info/top_level.txt
keypad_io-0.1.0.dist-info/RECORD
