Metadata-Version: 2.2
Name: keypad-io
Version: 0.1.0
Summary: An event-based Python keypad library for the Raspberry Pi
Author-email: TypeMonkey <anothertypemonkey@gmail.com>
Project-URL: Homepage, https://github.com/TypeMonkey/keypad-io
Project-URL: Issues, https://github.com/TypeMonkey/keypad-io/issues
Classifier: Programming Language :: Python :: 3
Classifier: License :: OSI Approved :: GNU General Public License v3 (GPLv3)
Classifier: Intended Audience :: Education
Classifier: Topic :: System :: Hardware
Requires-Python: >=3.11
License-File: LICENSE
